py_web/__init__.py
py_web/facebook.py
py_web/google.py
py_web/twitter.py
py_web/youtube.py
py_web-1.0.dist-info/LICENSE
py_web-1.0.dist-info/METADATA
py_web-1.0.dist-info/WHEEL
py_web-1.0.dist-info/top_level.txt
py_web-1.0.dist-info/RECORD
