Metadata-Version: 2.1
Name: py-web
Version: 1.0
Summary: Py_web is used for testing purpose only.
